setup.py
maths_package/__init__.py
maths_package/calculator.py
maths_package.egg-info/PKG-INFO
maths_package.egg-info/SOURCES.txt
maths_package.egg-info/dependency_links.txt
maths_package.egg-info/not-zip-safe
maths_package.egg-info/top_level.txt