Metadata-Version: 1.0
Name: maths-package
Version: 1.0
Summary: Maths calculator package
Home-page: UNKNOWN
Author: Darren Gidado
Author-email: myemail@something.com
License: UNKNOWN
Platform: UNKNOWN
